prophecy_deploy_cli_deps/__init__.py
prophecy_deploy_cli_deps/deploy-cli-standalone-v1.0.1-jpmc-bec9ef6/bin/hyperd
prophecy_deploy_cli_deps/deploy-cli-standalone-v1.0.1-jpmc-bec9ef6/bin/libTableauCppLibrary.so
prophecy_deploy_cli_deps/deploy-cli-standalone-v1.0.1-jpmc-bec9ef6/bin/libtableauhyperapi.so
prophecy_deploy_cli_deps-1.0.1.dist-info/METADATA
prophecy_deploy_cli_deps-1.0.1.dist-info/WHEEL
prophecy_deploy_cli_deps-1.0.1.dist-info/top_level.txt
prophecy_deploy_cli_deps-1.0.1.dist-info/RECORD
