Metadata-Version: 2.4
Name: prophecy-deploy-cli-deps
Version: 1.0.1
Summary: Prophecy Deploy CLI Dependencies (JPMC)
Author-email: Prophecy <support@prophecy.io>
License: Proprietary
Project-URL: Homepage, https://prophecy.io
Project-URL: Repository, https://github.com/prophecy-io/prophecy-deploy-cli-binary
Keywords: prophecy,deploy,cli,binary,dependencies
Classifier: Programming Language :: Python :: 3
Classifier: License :: Other/Proprietary License
Classifier: Operating System :: POSIX :: Linux
Requires-Python: >=3.8
